README
ipycache.py
setup.py
ipycache.egg-info/PKG-INFO
ipycache.egg-info/SOURCES.txt
ipycache.egg-info/dependency_links.txt
ipycache.egg-info/top_level.txt