Metadata-Version: 1.1
Name: ipycache
Version: 0.1.4
Summary: Defines a %%cache cell magic in the IPython notebook to cache results of long-lasting computations in a persistentpickle file.
Home-page: http://packages.python.org/ipycache
Author: Cyrille Rossant
Author-email: rossant@github
License: BSD
Keywords: ipython notebook cache
Platform: UNKNOWN
Classifier: Development Status :: 3 - Alpha
Classifier: Topic :: Utilities
Classifier: Framework :: IPython
Classifier: License :: OSI Approved :: BSD License
